threadsafe/dict.py
threadsafe/list.py
threadsafe/ordered_dict.py
threadsafe/safe_csv.py
threadsafe-1.0.0.dist-info/DESCRIPTION.rst
threadsafe-1.0.0.dist-info/METADATA
threadsafe-1.0.0.dist-info/RECORD
threadsafe-1.0.0.dist-info/WHEEL
threadsafe-1.0.0.dist-info/metadata.json
threadsafe-1.0.0.dist-info/top_level.txt
